clickhouse_driver_decorators/__init__.py
clickhouse_driver_decorators/abstract_decorator.py
clickhouse_driver_decorators/abstract_rows_processable_decorator.py
clickhouse_driver_decorators/add_column_names.py
clickhouse_driver_decorators/apply_callback.py
clickhouse_driver_decorators/convert_string_to_datetime.py
clickhouse_driver_decorators/convert_timestamp_to_datetime.py
clickhouse_driver_decorators/transform_to_pandas_dataframe.py
clickhouse_driver_decorators-0.2.0.dist-info/LICENSE
clickhouse_driver_decorators-0.2.0.dist-info/METADATA
clickhouse_driver_decorators-0.2.0.dist-info/WHEEL
clickhouse_driver_decorators-0.2.0.dist-info/top_level.txt
clickhouse_driver_decorators-0.2.0.dist-info/RECORD
