Metadata-Version: 2.1
Name: clickhouse-driver-decorators
Version: 0.2.0
Summary: Bunch of decorators to decorate clickhouse-driver's execute method
Home-page: https://github.com/Islam93/clickhouse-driver-decorators
Author: Islam Israfilov (Islam93)
Author-email: israfilov93@gmail.com
License: MIT
Platform: UNKNOWN
Requires-Python: >=3.5
Requires-Dist: pytz (>=2021.1)
Requires-Dist: pandas (>=0.25.3)
Requires-Dist: clickhouse-driver (>=0.1.3)
Provides-Extra: dev
Requires-Dist: pytest (>=6.1.2) ; extra == 'dev'
Requires-Dist: pytest-cov (>=2.11.1) ; extra == 'dev'
Requires-Dist: mock (>=3.0.5) ; extra == 'dev'
Requires-Dist: pylint (>=2.6.0) ; extra == 'dev'
Provides-Extra: test
Requires-Dist: pytest (>=6.1.2) ; extra == 'test'
Requires-Dist: pytest-cov (>=2.11.1) ; extra == 'test'
Requires-Dist: mock (>=3.0.5) ; extra == 'test'
